movoid_websocket/__init__.py
movoid_websocket/listener.py
movoid_websocket-1.0.2.dist-info/METADATA
movoid_websocket-1.0.2.dist-info/WHEEL
movoid_websocket-1.0.2.dist-info/top_level.txt
movoid_websocket-1.0.2.dist-info/RECORD
