Metadata-Version: 2.1
Name: movoid_websocket
Version: 1.0.2
Home-page: 
Author: movoid
Author-email: bobrobotsun@163.com
Requires-Dist: websocket-client
